beacons/__init__.py
beacons/beacons.py
beacons/definitions.py
beacons/cli/__init__.py
beacons/cli/config.py
beacons/cli/inventory.py
beacons/cli/main.py
beacons/cli/preferences.py
beacons/cli/publish.py
beacons/cli/script.py
beacons/cli/setup.py
beacons/cli/surreal.py
beacons/cli/task.py
beacons/cli/wingdbstub.py
beacons/cli/workspace.py
beacons/helpers/__init__.py
beacons/helpers/faker.py
beacons/helpers/general.py
beacons/helpers/loaders.py
beacons/helpers/models.py
beacons/helpers/surreal.py
beacons/logic/__init__.py
beacons/logic/beacons.py
beacons/logic/inventory.py
beacons/mappers/__init__.py
beacons/mappers/beacons.py
beacons/mappers/fiware.py
beacons/mappers/inventory.py
beacons/models/__init__.py
beacons/models/base.py
beacons/models/beacons.py
beacons/models/config.py
beacons/models/enums.py
beacons/models/fiware.py
beacons/models/inventory.py
beacons/models/script.py
beacons/models/task.py
beacons/ports/__init__.py
beacons/ports/beacons.py
beacons/ports/preferences.py
beacons/storage/__init__.py
beacons/storage/surreal.py
beacons-0.1.0.dist-info/AUTHORS.rst
beacons-0.1.0.dist-info/LICENSE
beacons-0.1.0.dist-info/METADATA
beacons-0.1.0.dist-info/WHEEL
beacons-0.1.0.dist-info/entry_points.txt
beacons-0.1.0.dist-info/top_level.txt
beacons-0.1.0.dist-info/RECORD
